LICENSE
MANIFEST.in
README
setup.py
django_any/__init__.py
django_any/forms.py
django_any/functions.py
django_any/models.py
django_any/test.py
django_any/xunit.py
django_any.egg-info/PKG-INFO
django_any.egg-info/SOURCES.txt
django_any.egg-info/dependency_links.txt
django_any.egg-info/not-zip-safe
django_any.egg-info/top_level.txt
django_any/contrib/__init__.py
django_any/contrib/auth.py
django_any/tests/__init__.py
django_any/tests/any_field_tests.py
django_any/tests/any_forms_tests.py
django_any/tests/any_model_tests.py
django_any/tests/any_user_tests.py
django_any/tests/test_client_tests.py
django_any/tests/test_set_seed_tests.py
docs/quickstart.txt