Metadata-Version: 1.0
Name: django-any
Version: 0.2.0
Summary: Unobtrusive test models  creation for django.
Home-page: http://github.com/kmmbvnr/django-any
Author: Mikhail Podgurskiy
Author-email: kmmbvnr@gmail.com
License: MIT License
Keywords: django
Platform: any
Classifier: Development Status :: 3 - Alpha
Classifier: Environment :: Web Environment
Classifier: Intended Audience :: Developers
Classifier: License :: OSI Approved :: MIT License
Classifier: Operating System :: OS Independent
Classifier: Programming Language :: Python
Classifier: Framework :: Django
